{
  "capturedAt": "2026-04-03T01:55:50.050Z",
  "taskId": "cf7c75b3-8d81-4486-96c0-079647f7b1cc",
  "runId": "9bdd198f-86ea-453e-a8ee-5f04b907189c",
  "taskName": "probe_data_api",
  "startDate": "2023-01-01",
  "endDate": "2023-12-31",
  "capital": 100000,
  "success": true,
  "state": "completed",
  "executions": [
    {
      "taskId": "cf7c75b3-8d81-4486-96c0-079647f7b1cc",
      "runId": "9bdd198f-86ea-453e-a8ee-5f04b907189c",
      "source": "\"\"\"\nBigQuant 数据 API 探测\n测试各类数据接口是否可用\n\"\"\"\nimport traceback\n\nresults = {}\n\ndef test(name, fn):\n    try:\n        r = fn()\n        results[name] = ('OK', str(r)[:200] if r is not None else 'None')\n        ",
      "status": "ok",
      "textOutput": "=== BigQuant 数据 API 探测 ===\n\n--- DAI API ---\n✓ dai.query stocks:         date instrument         open         high          low        close  \\\n0 2024-01-02  000001.\n✓ dai.query fundamentals:         date instrument     pe_ttm        pb\n0 2024-01-02  000001.SZ   3.685732  0.383653\n1 2024-01-\n✗ dai.query index: Invalid Input Error: Attempting to execute an unsuccessful or closed pending query result\nError: Catalog Error: Table with name cn_index_bar1d does not exist!\nDid you mean \"pg_index\"?\n\nLINE 1: SELECT date, instrument, \"close\" FROM cn_index_bar1d WHERE ((instrument = '000300.SH') AND ...\n                                            ^\n\n--- BigQuant 内置 API ---\n✓ bigquant 版本: unknown\n✓ bigquant.get_instruments: N/A\n\n--- bq 模块 ---\n✗ bq 模块: No module named 'bq'\n\n--- 其他数据模块 ---\n✗ akshare 不可用\n✓ tushare 可用: 1.4.6\n✗ yfinance 不可用\n✓ pandas_datareader 可用: 0.10.0\n\n--- 已安装的量化相关包 ---\n  bigquant 0.1.0.post28+g95c2859\n  pyfinance 1.3.0\n  tushare 1.4.6\n\n=== 探测完成 ===",
      "outputs": [],
      "logs": [
        "2026-04-03 09:55:40 任务运行开始调度 state=trigger event= cf7c75b3-8d81-4486-96c0-079647f7b1cc ..",
        "2026-04-03 09:55:43 任务运行状态更新 state=scheduled event=20260402 cf7c75b3-8d81-4486-96c0-079647f7b1cc",
        "2026-04-03 09:55:46 任务运行状态更新 state=running event=20260402 cf7c75b3-8d81-4486-96c0-079647f7b1cc",
        "2026-04-03 09:55:46 [info     ] run task_id='cf7c75b3-8d81-4486-96c0-079647f7b1cc' ..",
        "2026-04-03 09:55:46 [info     ] fetch task cf7c75b3-8d81-4486-96c0-079647f7b1cc ..",
        "2026-04-03 09:55:46 [info     ] start cf7c75b3-8d81-4486-96c0-079647f7b1cc ..",
        "=== BigQuant 数据 API 探测 ===",
        "",
        "--- DAI API ---",
        "✓ dai.query stocks:         date instrument         open         high          low        close  \\",
        "0 2024-01-02  000001.",
        "✓ dai.query fundamentals:         date instrument     pe_ttm        pb",
        "0 2024-01-02  000001.SZ   3.685732  0.383653",
        "1 2024-01-",
        "✗ dai.query index: Invalid Input Error: Attempting to execute an unsuccessful or closed pending query result",
        "Error: Catalog Error: Table with name cn_index_bar1d does not exist!",
        "Did you mean \"pg_index\"?",
        "",
        "LINE 1: SELECT date, instrument, \"close\" FROM cn_index_bar1d WHERE ((instrument = '000300.SH') AND ...",
        "                                            ^",
        "",
        "--- BigQuant 内置 API ---",
        "✓ bigquant 版本: unknown",
        "✓ bigquant.get_instruments: N/A",
        "",
        "--- bq 模块 ---",
        "✗ bq 模块: No module named 'bq'",
        "",
        "--- 其他数据模块 ---",
        "✗ akshare 不可用",
        "✓ tushare 可用: 1.4.6",
        "✗ yfinance 不可用",
        "✓ pandas_datareader 可用: 0.10.0",
        "",
        "--- 已安装的量化相关包 ---",
        "  bigquant 0.1.0.post28+g95c2859",
        "  pyfinance 1.3.0",
        "  tushare 1.4.6",
        "",
        "=== 探测完成 ===",
        "2026-04-03 09:55:49 [info     ] done.",
        "2026-04-03 09:55:49 任务运行状态更新 state=completed event=20260402 cf7c75b3-8d81-4486-96c0-079647f7b1cc"
      ]
    }
  ]
}