{
  "capturedAt": "2026-03-29T06:06:55.944Z",
  "cookies": [
    {
      "name": "_xsrf",
      "value": "2|227d94e7|406c29691b19f33d4c690dc5155194ea|1774764407",
      "domain": "guorn.com",
      "path": "/",
      "expires": -1,
      "httpOnly": false,
      "secure": false,
      "sameSite": "Lax"
    },
    {
      "name": "uname",
      "value": "\"2|1:0|10:1774764411|5:uname|12:eXVwaW5nMzIy|4e25ae3a63cc92d57a1fe4a5f4d9e874ad1666671c36c221545a9fa91aa7b5c1\"",
      "domain": "guorn.com",
      "path": "/",
      "expires": -1,
      "httpOnly": true,
      "secure": false,
      "sameSite": "Lax"
    },
    {
      "name": "account",
      "value": "\"2|1:0|10:1774764411|7:account|16:MTMzMTEzOTAzMjM=|2f7dbbda91139923bce87573ef4dd38044c478c1aaff17c553e641e9cb78a5c2\"",
      "domain": "guorn.com",
      "path": "/",
      "expires": -1,
      "httpOnly": true,
      "secure": false,
      "sameSite": "Lax"
    },
    {
      "name": "user",
      "value": "\"2|1:0|10:1774764411|4:user|12:MjgwMjEyOA==|d1ca657c460e207a64d8831c25d103dbb0b10ec2c073b4df383da77e9c8e714b\"",
      "domain": "guorn.com",
      "path": "/",
      "expires": -1,
      "httpOnly": true,
      "secure": false,
      "sameSite": "Lax"
    },
    {
      "name": "token",
      "value": "\"2|1:0|10:1774764411|5:token|76:N2IyZWY0ZjJlODI2NGJjY2JhNmRjMzVjOGU3MTZhYzI3Y2FhNjY1ZTNlYWM4ZjMzYWEyMzEzZGQ=|9b530b28260b24a6d5a8c41c4c84cd1f40d538d7ca171b7c9e972b084553c4ad\"",
      "domain": "guorn.com",
      "path": "/",
      "expires": -1,
      "httpOnly": true,
      "secure": false,
      "sameSite": "Lax"
    },
    {
      "name": "HMACCOUNT_BFESS",
      "value": "6D1AF6EF37F1CD98",
      "domain": ".hm.baidu.com",
      "path": "/",
      "expires": 1809324411.310182,
      "httpOnly": false,
      "secure": true,
      "sameSite": "None"
    },
    {
      "name": "Hm_lvt_40ee94ccee2cf1051316f73e3fbcf8ac",
      "value": "1774764411",
      "domain": ".guorn.com",
      "path": "/",
      "expires": 1806300411,
      "httpOnly": false,
      "secure": false,
      "sameSite": "Lax"
    },
    {
      "name": "Hm_lpvt_40ee94ccee2cf1051316f73e3fbcf8ac",
      "value": "1774764411",
      "domain": ".guorn.com",
      "path": "/",
      "expires": -1,
      "httpOnly": false,
      "secure": false,
      "sameSite": "Lax"
    },
    {
      "name": "HMACCOUNT",
      "value": "6D1AF6EF37F1CD98",
      "domain": ".guorn.com",
      "path": "/",
      "expires": -1,
      "httpOnly": false,
      "secure": false,
      "sameSite": "Lax"
    },
    {
      "name": "_ga",
      "value": "GA1.2.877917134.1774764412",
      "domain": ".guorn.com",
      "path": "/",
      "expires": 1809324412.11011,
      "httpOnly": false,
      "secure": false,
      "sameSite": "Lax"
    },
    {
      "name": "_gid",
      "value": "GA1.2.1829998770.1774764412",
      "domain": ".guorn.com",
      "path": "/",
      "expires": 1774850812,
      "httpOnly": false,
      "secure": false,
      "sameSite": "Lax"
    },
    {
      "name": "_gat",
      "value": "1",
      "domain": ".guorn.com",
      "path": "/",
      "expires": 1774764472,
      "httpOnly": false,
      "secure": false,
      "sameSite": "Lax"
    },
    {
      "name": "_ga_F86HQLY9XG",
      "value": "GS2.2.s1774764413$o1$g0$t1774764413$j60$l0$h0",
      "domain": ".guorn.com",
      "path": "/",
      "expires": 1809324413.897293,
      "httpOnly": false,
      "secure": false,
      "sameSite": "Lax"
    }
  ]
}